{ "autotag": [{ "name": "Human", "confidence": 98.786819458008 },{ "name": "Person", "confidence": 98.786819458008 },{ "name": "Crowd", "confidence": 97.452156066895 },{ "name": "Audience", "confidence": 97.11360168457 },{ "name": "Stage", "confidence": 93.65641784668 },{ "name": "Speech", "confidence": 90.970565795898 },{ "name": "Apparel", "confidence": 68.225746154785 },{ "name": "Clothing", "confidence": 68.225746154785 },{ "name": "Sitting", "confidence": 62.473388671875 },{ "name": "Chair", "confidence": 61.754138946533 },{ "name": "Furniture", "confidence": 61.754138946533 },{ "name": "Press Conference", "confidence": 61.57247543335 },{ "name": "Face", "confidence": 60.582382202148 },{ "name": "Pottery", "confidence": 59.120212554932 },{ "name": "Performer", "confidence": 58.675819396973 },{ "name": "Potted Plant", "confidence": 57.160598754883 },{ "name": "Jar", "confidence": 57.160598754883 },{ "name": "Vase", "confidence": 57.160598754883 },{ "name": "Plant", "confidence": 57.160598754883 },{}]}