{ "autotag": [{ "name": "Human", "confidence": 99.408058166504 },{ "name": "Person", "confidence": 99.408058166504 },{ "name": "Crowd", "confidence": 99.408058166504 },{ "name": "Audience", "confidence": 96.435470581055 },{ "name": "Coat", "confidence": 94.526062011719 },{ "name": "Overcoat", "confidence": 94.526062011719 },{ "name": "Apparel", "confidence": 94.526062011719 },{ "name": "Suit", "confidence": 94.526062011719 },{ "name": "Clothing", "confidence": 94.526062011719 },{ "name": "Tie", "confidence": 93.364685058594 },{ "name": "Accessories", "confidence": 93.364685058594 },{ "name": "Accessory", "confidence": 93.364685058594 },{ "name": "Speech", "confidence": 87.006790161133 },{ "name": "Press Conference", "confidence": 84.492477416992 },{ "name": "Lecture", "confidence": 61.109760284424 },{}]}