{ "autotag": [{ "name": "Person", "confidence": 99.686920166016 },{ "name": "Human", "confidence": 99.686920166016 },{ "name": "Room", "confidence": 82.611770629883 },{ "name": "Indoors", "confidence": 82.611770629883 },{ "name": "Court", "confidence": 81.715065002441 },{ "name": "Accessories", "confidence": 72.69287109375 },{ "name": "Accessory", "confidence": 72.69287109375 },{ "name": "Sunglasses", "confidence": 72.69287109375 },{ "name": "Priest", "confidence": 67.899887084961 },{ "name": "Crowd", "confidence": 63.118721008301 },{ "name": "People", "confidence": 61.596580505371 },{ "name": "Bishop", "confidence": 58.345436096191 },{ "name": "Glasses", "confidence": 57.672309875488 },{}]}